{
  "text": [
    {
      "text": "Always keep subscribers in loop with **Evergreen Campaigns**:",
      "variant": "h2"
    },
    {
      "text": "Create a broadcast that stays relevant at all times and can be sent over and over again at regular intervals. With evergreen campaigns, Mumara can be assigned to keep sending the same broadcast as many times as desired according to the defined frequency.",
      "variant": "medium"
    }
  ],
  "images": [
    {
      "src": "../../../../assets/flexiblocks/sms/inner/1-1.png",
      "radius": "lg",
      "alt": "Importing",
      "effects": ["fadeInLeft", "float"]
    }
  ]
}
